{
    "productAttr": null,
    "productCommentSummary": {
        "skuId": 12094006027,
        "averageScore": 5,
        "defaultGoodCount": 2901,
        "defaultGoodCountStr": "2900+",
        "commentCount": 6536,
        "commentCountStr": "6500+",
        "goodCount": 6208,
        "goodCountStr": "6200+",
        "goodRate": 0.99,
        "goodRateShow": 99,
        "generalCount": 14,
        "generalCountStr": "10+",
        "generalRate": 0.009,
        "generalRateShow": 1,
        "poorCount": 10,
        "poorCountStr": "10",
        "poorRate": 0.001,
        "poorRateShow": 0,
        "videoCount": 0,
        "videoCountStr": "0",
        "afterCount": 111,
        "afterCountStr": "100+",
        "showCount": 28,
        "showCountStr": "20+",
        "oneYear": 0,
        "sensitiveBook": 0,
        "fixCount": 2597,
        "plusCount": 0,
        "plusCountStr": "0",
        "buyerShow": 0,
        "poorRateStyle": 0,
        "generalRateStyle": 2,
        "goodRateStyle": 148,
        "installRate": 0,
        "productId": 12094006027,
        "score1Count": 10,
        "score2Count": 4,
        "score3Count": 10,
        "score4Count": 61,
        "score5Count": 3550
    },
    "hotCommentTagStatistics": [
        {
            "id": "bb4c03cebcba890a",
            "name": "做工精湛",
            "count": 3,
            "type": 4,
            "canBeFiltered": true,
            "stand": 1,
            "rid": "bb4c03cebcba890a",
            "ckeKeyWordBury": "eid=100^^tagid=bb4c03cebcba890a^^pid=20027^^sku=12094006027^^sversion=1000^^token=bd11314b3bf4614e"
        },
        {
            "id": "7ad4b7e72e23b40d",
            "name": "品相一流",
            "count": 2,
            "type": 4,
            "canBeFiltered": true,
            "stand": 1,
            "rid": "7ad4b7e72e23b40d",
            "ckeKeyWordBury": "eid=100^^tagid=7ad4b7e72e23b40d^^pid=20027^^sku=12094006027^^sversion=1000^^token=cc13347aa0869053"
        },
        {
            "id": "6640172dc525e1a4",
            "name": "毫无异味",
            "count": 2,
            "type": 4,
            "canBeFiltered": true,
            "stand": 1,
            "rid": "6640172dc525e1a4",
            "ckeKeyWordBury": "eid=100^^tagid=6640172dc525e1a4^^pid=20027^^sku=12094006027^^sversion=1000^^token=bbaa853c908c6fb5"
        },
        {
            "id": "be4c76ce01b83386",
            "name": "简单方便",
            "count": 1,
            "type": 4,
            "canBeFiltered": true,
            "stand": 1,
            "rid": "be4c76ce01b83386",
            "ckeKeyWordBury": "eid=100^^tagid=be4c76ce01b83386^^pid=20027^^sku=12094006027^^sversion=1000^^token=64e894f04e423704"
        },
        {
            "id": "2aa5d521db4d0cb6",
            "name": "超级好用",
            "count": 1,
            "type": 4,
            "canBeFiltered": true,
            "stand": 1,
            "rid": "2aa5d521db4d0cb6",
            "ckeKeyWordBury": "eid=100^^tagid=2aa5d521db4d0cb6^^pid=20027^^sku=12094006027^^sversion=1000^^token=48ea6bcb0d080fe8"
        },
        {
            "id": "7e3c069b0a285d9b",
            "name": "体感舒适",
            "count": 1,
            "type": 4,
            "canBeFiltered": true,
            "stand": 1,
            "rid": "7e3c069b0a285d9b",
            "ckeKeyWordBury": "eid=100^^tagid=7e3c069b0a285d9b^^pid=20027^^sku=12094006027^^sversion=1000^^token=0518a89fc66a0827"
        },
        {
            "id": "f4aa969bb9e5a378",
            "name": "样式美观",
            "count": 1,
            "type": 4,
            "canBeFiltered": true,
            "stand": 1,
            "rid": "f4aa969bb9e5a378",
            "ckeKeyWordBury": "eid=100^^tagid=f4aa969bb9e5a378^^pid=20027^^sku=12094006027^^sversion=1000^^token=ca30481a094d1ca2"
        },
        {
            "id": "cfceac32bbcbdd7e",
            "name": "质感一流",
            "count": 1,
            "type": 4,
            "canBeFiltered": true,
            "stand": 1,
            "rid": "cfceac32bbcbdd7e",
            "ckeKeyWordBury": "eid=100^^tagid=cfceac32bbcbdd7e^^pid=20027^^sku=12094006027^^sversion=1000^^token=c96e13c6592d539b"
        },
        {
            "id": "f96710e3a1e672e0",
            "name": "身体舒适",
            "count": 1,
            "type": 4,
            "canBeFiltered": true,
            "stand": 1,
            "rid": "f96710e3a1e672e0",
            "ckeKeyWordBury": "eid=100^^tagid=f96710e3a1e672e0^^pid=20027^^sku=12094006027^^sversion=1000^^token=3ab346a88c789f06"
        }
    ],
    "jwotestProduct": null,
    "maxPage": 100,
    "testId": "cmt",
    "score": 0,
    "soType": 5,
    "imageListCount": 69,
    "vTagStatistics": null,
    "csv": "eid=100^^tagid=ALL^^pid=20027^^sku=10326528331^^sversion=1001^^pageSize=3",
    "comments": [
        {
            "id": 11687376872,
            "guid": "84d45e99-4416-42fb-ae32-f48612ce609f",
            "content": "物与图片相似度98%，没有色差，实物是全tpe制作的，肉感十足，差的是卖家的图片都没有我自己打扮拍起来的好看！摸起来和用起来与真人相似，卖家没有夸大其词。值得购买。建议狼友们们买大号的好用些。也希望卖家保正质量的同时在重量上再改进些，轻些用起来会更方便。真的很满意！想不到国内也有如此水平了！不用再去买那些几万快的了！&lsquo;",
            "creationTime": "2018-07-09 16:40:12",
            "isDelete": false,
            "isTop": false,
            "userImageUrl": "misc.360buyimg.com/user/myjd-2015/css/i/peisong.jpg",
            "topped": 0,
            "replies": [
                {
                    "id": 369177981,
                    "commentId": 11687376872,
                    "content": "深情不及久伴，厚爱无需多言，感谢您对弘利的支持与信赖。祝您生活愉快！",
                    "pin": "h***8",
                    "userClient": 98,
                    "userImage": "misc.360buyimg.com/user/myjd-2015/css/i/peisong.jpg",
                    "ip": "127.0.0.1",
                    "productId": 12094006022,
                    "replyList": [],
                    "nickname": "h***8",
                    "creationTime": "2018-08-29 15:20:20",
                    "parentId": 0,
                    "targetId": 0,
                    "venderShopInfo": {
                        "id": 638943,
                        "appName": "//mall.jd.com/index-638943.html",
                        "title": "弘利成人用品专营店",
                        "venderId": 643103
                    }
                }
            ],
            "replyCount": 1,
            "score": 5,
            "title": "",
            "usefulVoteCount": 1,
            "userClient": 2,
            "anonymousFlag": 1,
            "plusAvailable": 0,
            "mobileVersion": "7.0.7",
            "productColor": "1.15米（可选站立款）",
            "productSize": "",
            "textIntegral": 40,
            "status": 1,
            "referenceId": "12094006022",
            "referenceTime": "2018-07-06 12:04:28",
            "nickname": "j***董",
            "replyCount2": 1,
            "userImage": "misc.360buyimg.com/user/myjd-2015/css/i/peisong.jpg",
            "orderId": 0,
            "integral": 40,
            "productSales": "[]",
            "referenceImage": "jfs/t1/86868/7/9040/326789/5e0aa6d0E1910d92b/edc794bc79b1152d.jpg",
            "referenceName": "公主（gongzhu）实体娃娃男用免充气全硅胶带骨骼美女仿真人 阴臀倒模自慰器具成人情趣性用品 灵儿 1.15米（可选站立款）",
            "firstCategory": 9192,
            "secondCategory": 9196,
            "thirdCategory": 14697,
            "aesPin": null,
            "days": 3,
            "afterDays": 0
        },
        {
            "id": 11644150547,
            "guid": "24107139-497c-4da8-8305-4653634df226",
            "content": "今天来补充两点:①快递小哥(娘家送亲客)亲自背上楼把娃娃送进婆家，服务甚佳，在此表示衷心地感谢！②厂家发明制造出了优质的功能齐全的美丽动人的实体娃娃是一大创举，为就业提供了岗位，为财政创造了收入，也为常去逛窑子的哥们省下了一大笔钱，特别是为社会治安作出了巨大的贡献，特为厂家辛勤工作的领导和员工们赞一个！",
            "creationTime": "2018-06-26 15:59:18",
            "isDelete": false,
            "isTop": false,
            "userImageUrl": "misc.360buyimg.com/user/myjd-2015/css/i/peisong.jpg",
            "topped": 0,
            "replies": [
                {
                    "id": 369177061,
                    "commentId": 11644150547,
                    "content": "深情不及久伴，厚爱无需多言，感谢您对弘利的支持与信赖。祝您生活愉快！",
                    "pin": "h***8",
                    "userClient": 98,
                    "userImage": "misc.360buyimg.com/user/myjd-2015/css/i/peisong.jpg",
                    "ip": "127.0.0.1",
                    "productId": 12094006022,
                    "replyList": [],
                    "nickname": "h***8",
                    "creationTime": "2018-08-29 15:19:51",
                    "parentId": 0,
                    "targetId": 0,
                    "venderShopInfo": {
                        "id": 638943,
                        "appName": "//mall.jd.com/index-638943.html",
                        "title": "弘利成人用品专营店",
                        "venderId": 643103
                    }
                }
            ],
            "replyCount": 1,
            "score": 5,
            "title": "",
            "usefulVoteCount": 1,
            "userClient": 2,
            "anonymousFlag": 1,
            "plusAvailable": 0,
            "mobileVersion": "7.0.4",
            "productColor": "1.15米（可选站立款）",
            "productSize": "",
            "textIntegral": 40,
            "status": 1,
            "referenceId": "12094006022",
            "referenceTime": "2018-06-23 11:13:34",
            "nickname": "j***b",
            "replyCount2": 1,
            "userImage": "misc.360buyimg.com/user/myjd-2015/css/i/peisong.jpg",
            "orderId": 0,
            "integral": 40,
            "productSales": "[]",
            "referenceImage": "jfs/t1/86868/7/9040/326789/5e0aa6d0E1910d92b/edc794bc79b1152d.jpg",
            "referenceName": "公主（gongzhu）实体娃娃男用免充气全硅胶带骨骼美女仿真人 阴臀倒模自慰器具成人情趣性用品 灵儿 1.15米（可选站立款）",
            "firstCategory": 9192,
            "secondCategory": 9196,
            "thirdCategory": 14697,
            "aesPin": null,
            "days": 3,
            "afterDays": 0
        },
        {
            "id": 13729094405,
            "guid": "45d48181-b5c4-46fb-8376-a78df06fbbf3",
            "content": "价格实惠，质量好，非常满意",
            "creationTime": "2020-01-16 11:14:18",
            "isDelete": false,
            "isTop": false,
            "userImageUrl": "misc.360buyimg.com/user/myjd-2015/css/i/peisong.jpg",
            "topped": 0,
            "replyCount": 0,
            "score": 5,
            "title": "",
            "usefulVoteCount": 0,
            "userClient": 2,
            "anonymousFlag": 1,
            "plusAvailable": 0,
            "mobileVersion": "",
            "productColor": "1.15米（可选站立款）",
            "productSize": "",
            "textIntegral": 40,
            "status": 1,
            "referenceId": "12094006027",
            "referenceTime": "2020-01-13 16:30:16",
            "nickname": "j***H",
            "replyCount2": 0,
            "userImage": "misc.360buyimg.com/user/myjd-2015/css/i/peisong.jpg",
            "orderId": 0,
            "integral": 40,
            "productSales": "[]",
            "referenceImage": "jfs/t1/86868/7/9040/326789/5e0aa6d0E1910d92b/edc794bc79b1152d.jpg",
            "referenceName": "公主（gongzhu）实体娃娃男用免充气全硅胶带骨骼美女仿真人 阴臀倒模自慰器具成人情趣性用品 灵儿 1.15米（可选站立款）",
            "firstCategory": 9192,
            "secondCategory": 9196,
            "thirdCategory": 14697,
            "aesPin": null,
            "days": 3,
            "afterDays": 0
        },
        {
            "id": 13724776524,
            "guid": "39a50838-7774-4c6e-8dbd-a57c439f4c24",
            "content": "娃娃非常逼真，各种姿势都可以玩，现在基本每天都要玩一下，太喜欢了",
            "creationTime": "2020-01-15 09:39:16",
            "isDelete": false,
            "isTop": false,
            "userImageUrl": "misc.360buyimg.com/user/myjd-2015/css/i/peisong.jpg",
            "topped": 0,
            "replyCount": 0,
            "score": 5,
            "title": "",
            "usefulVoteCount": 0,
            "userClient": 2,
            "anonymousFlag": 1,
            "plusAvailable": 0,
            "mobileVersion": "",
            "productColor": "1.15米（可选站立款）",
            "productSize": "",
            "textIntegral": 20,
            "status": 1,
            "referenceId": "12094006027",
            "referenceTime": "2020-01-12 14:00:55",
            "nickname": "j***n",
            "replyCount2": 0,
            "userImage": "misc.360buyimg.com/user/myjd-2015/css/i/peisong.jpg",
            "orderId": 0,
            "integral": 20,
            "productSales": "[]",
            "referenceImage": "jfs/t1/86868/7/9040/326789/5e0aa6d0E1910d92b/edc794bc79b1152d.jpg",
            "referenceName": "公主（gongzhu）实体娃娃男用免充气全硅胶带骨骼美女仿真人 阴臀倒模自慰器具成人情趣性用品 灵儿 1.15米（可选站立款）",
            "firstCategory": 9192,
            "secondCategory": 9196,
            "thirdCategory": 14697,
            "aesPin": null,
            "days": 3,
            "afterDays": 0
        },
        {
            "id": 13726223884,
            "guid": "074a808c-1c24-4eb5-9b69-d79dee3cb5f5",
            "content": "物流很及时，这个价位买到满意",
            "creationTime": "2020-01-15 15:42:19",
            "isDelete": false,
            "isTop": false,
            "userImageUrl": "misc.360buyimg.com/user/myjd-2015/css/i/peisong.jpg",
            "topped": 0,
            "replyCount": 0,
            "score": 5,
            "title": "",
            "usefulVoteCount": 0,
            "userClient": 2,
            "anonymousFlag": 1,
            "plusAvailable": 0,
            "mobileVersion": "",
            "productColor": "1.15米（可选站立款）",
            "productSize": "",
            "textIntegral": 20,
            "status": 1,
            "referenceId": "12094006027",
            "referenceTime": "2020-01-12 15:55:46",
            "nickname": "j***U",
            "replyCount2": 0,
            "userImage": "misc.360buyimg.com/user/myjd-2015/css/i/peisong.jpg",
            "orderId": 0,
            "integral": 20,
            "productSales": "[]",
            "referenceImage": "jfs/t1/86868/7/9040/326789/5e0aa6d0E1910d92b/edc794bc79b1152d.jpg",
            "referenceName": "公主（gongzhu）实体娃娃男用免充气全硅胶带骨骼美女仿真人 阴臀倒模自慰器具成人情趣性用品 灵儿 1.15米（可选站立款）",
            "firstCategory": 9192,
            "secondCategory": 9196,
            "thirdCategory": 14697,
            "aesPin": null,
            "days": 3,
            "afterDays": 0
        },
        {
            "id": 13726125676,
            "guid": "8630e073-520e-4da1-b29d-94b34a48fc26",
            "content": "给快递好评，满分好评太给力了",
            "creationTime": "2020-01-15 15:17:57",
            "isDelete": false,
            "isTop": false,
            "userImageUrl": "misc.360buyimg.com/user/myjd-2015/css/i/peisong.jpg",
            "topped": 0,
            "replyCount": 0,
            "score": 5,
            "usefulVoteCount": 0,
            "userClient": 2,
            "anonymousFlag": 1,
            "plusAvailable": 0,
            "mobileVersion": "",
            "productColor": "1.15米（可选站立款）",
            "textIntegral": 40,
            "status": 1,
            "referenceId": "12094006027",
            "referenceTime": "2020-01-12 14:39:43",
            "nickname": "j***b",
            "replyCount2": 0,
            "userImage": "misc.360buyimg.com/user/myjd-2015/css/i/peisong.jpg",
            "orderId": 0,
            "integral": 40,
            "productSales": "[]",
            "referenceImage": "jfs/t1/86868/7/9040/326789/5e0aa6d0E1910d92b/edc794bc79b1152d.jpg",
            "referenceName": "公主（gongzhu）实体娃娃男用免充气全硅胶带骨骼美女仿真人 阴臀倒模自慰器具成人情趣性用品 灵儿 1.15米（可选站立款）",
            "firstCategory": 9192,
            "secondCategory": 9196,
            "thirdCategory": 14697,
            "aesPin": null,
            "days": 3,
            "afterDays": 0
        },
        {
            "id": 13724745713,
            "guid": "a0c94110-fe4a-482d-a3a7-1fc76caca907",
            "content": "收到货了很惊喜，开始担心发货过来的时候会被别人发现，但卖家包装的很隐秘，一点都没有显露出来。娃娃质量不错，手感很好。没有什么气味，满意",
            "creationTime": "2020-01-15 09:30:45",
            "isDelete": false,
            "isTop": false,
            "userImageUrl": "misc.360buyimg.com/user/myjd-2015/css/i/peisong.jpg",
            "topped": 0,
            "replyCount": 0,
            "score": 5,
            "title": "",
            "usefulVoteCount": 0,
            "userClient": 2,
            "anonymousFlag": 1,
            "plusAvailable": 0,
            "mobileVersion": "",
            "productColor": "1.15米（可选站立款）",
            "productSize": "",
            "textIntegral": 0,
            "status": 1,
            "referenceId": "12094006027",
            "referenceTime": "2020-01-12 13:25:10",
            "nickname": "j***f",
            "replyCount2": 0,
            "userImage": "misc.360buyimg.com/user/myjd-2015/css/i/peisong.jpg",
            "orderId": 0,
            "integral": 0,
            "productSales": "[]",
            "referenceImage": "jfs/t1/86868/7/9040/326789/5e0aa6d0E1910d92b/edc794bc79b1152d.jpg",
            "referenceName": "公主（gongzhu）实体娃娃男用免充气全硅胶带骨骼美女仿真人 阴臀倒模自慰器具成人情趣性用品 灵儿 1.15米（可选站立款）",
            "firstCategory": 9192,
            "secondCategory": 9196,
            "thirdCategory": 14697,
            "aesPin": null,
            "days": 3,
            "afterDays": 0
        },
        {
            "id": 13722206708,
            "guid": "479d02b4-7a90-4c13-ae78-5f22da5a3c55",
            "content": "确实是单身的福利。玩着非常真实，很好用，这样玩起来超级舒服，",
            "creationTime": "2020-01-14 15:30:32",
            "isDelete": false,
            "isTop": false,
            "userImageUrl": "misc.360buyimg.com/user/myjd-2015/css/i/peisong.jpg",
            "topped": 0,
            "replyCount": 0,
            "score": 5,
            "title": "",
            "usefulVoteCount": 0,
            "userClient": 2,
            "anonymousFlag": 1,
            "plusAvailable": 0,
            "mobileVersion": "",
            "productColor": "1.15米（可选站立款）",
            "productSize": "",
            "textIntegral": 20,
            "status": 1,
            "referenceId": "12094006027",
            "referenceTime": "2020-01-11 14:14:53",
            "nickname": "j***D",
            "replyCount2": 0,
            "userImage": "misc.360buyimg.com/user/myjd-2015/css/i/peisong.jpg",
            "orderId": 0,
            "integral": 20,
            "productSales": "[]",
            "referenceImage": "jfs/t1/86868/7/9040/326789/5e0aa6d0E1910d92b/edc794bc79b1152d.jpg",
            "referenceName": "公主（gongzhu）实体娃娃男用免充气全硅胶带骨骼美女仿真人 阴臀倒模自慰器具成人情趣性用品 灵儿 1.15米（可选站立款）",
            "firstCategory": 9192,
            "secondCategory": 9196,
            "thirdCategory": 14697,
            "aesPin": null,
            "days": 3,
            "afterDays": 0
        },
        {
            "id": 13722144172,
            "guid": "4df2189a-1170-4087-8451-66ed7410f802",
            "content": "东西非常好用，材质包括柔软度都非常到位，非常建议大家购买。好用的很，好用的很。 保密工作做的非常到位，物流很快。",
            "creationTime": "2020-01-14 15:14:34",
            "isDelete": false,
            "isTop": false,
            "userImageUrl": "misc.360buyimg.com/user/myjd-2015/css/i/peisong.jpg",
            "topped": 0,
            "replyCount": 0,
            "score": 5,
            "usefulVoteCount": 0,
            "userClient": 2,
            "anonymousFlag": 1,
            "plusAvailable": 0,
            "mobileVersion": "",
            "productColor": "1.15米（可选站立款）",
            "textIntegral": 40,
            "status": 1,
            "referenceId": "12094006027",
            "referenceTime": "2020-01-11 12:00:24",
            "nickname": "j***K",
            "replyCount2": 0,
            "userImage": "misc.360buyimg.com/user/myjd-2015/css/i/peisong.jpg",
            "orderId": 0,
            "integral": 40,
            "productSales": "[]",
            "referenceImage": "jfs/t1/86868/7/9040/326789/5e0aa6d0E1910d92b/edc794bc79b1152d.jpg",
            "referenceName": "公主（gongzhu）实体娃娃男用免充气全硅胶带骨骼美女仿真人 阴臀倒模自慰器具成人情趣性用品 灵儿 1.15米（可选站立款）",
            "firstCategory": 9192,
            "secondCategory": 9196,
            "thirdCategory": 14697,
            "aesPin": null,
            "days": 3,
            "afterDays": 0
        },
        {
            "id": 13722223758,
            "guid": "1db5bf16-2896-485a-bf0e-dae7823e280a",
            "content": "特别销魂，用起来特别爽，有点像我和初恋第一次嘿咻的感脚小惊喜！东西给力",
            "creationTime": "2020-01-14 15:34:20",
            "isDelete": false,
            "isTop": false,
            "userImageUrl": "misc.360buyimg.com/user/myjd-2015/css/i/peisong.jpg",
            "topped": 0,
            "replyCount": 0,
            "score": 5,
            "title": "",
            "usefulVoteCount": 0,
            "userClient": 2,
            "anonymousFlag": 1,
            "plusAvailable": 0,
            "mobileVersion": "",
            "productColor": "1.15米（可选站立款）",
            "productSize": "",
            "textIntegral": 40,
            "status": 1,
            "referenceId": "12094006027",
            "referenceTime": "2020-01-11 14:47:57",
            "nickname": "j***x",
            "replyCount2": 0,
            "userImage": "misc.360buyimg.com/user/myjd-2015/css/i/peisong.jpg",
            "orderId": 0,
            "integral": 40,
            "productSales": "[]",
            "referenceImage": "jfs/t1/86868/7/9040/326789/5e0aa6d0E1910d92b/edc794bc79b1152d.jpg",
            "referenceName": "公主（gongzhu）实体娃娃男用免充气全硅胶带骨骼美女仿真人 阴臀倒模自慰器具成人情趣性用品 灵儿 1.15米（可选站立款）",
            "firstCategory": 9192,
            "secondCategory": 9196,
            "thirdCategory": 14697,
            "aesPin": null,
            "days": 3,
            "afterDays": 0
        }
    ]
}