{
    "productAttr": null,
    "productCommentSummary": {
        "skuId": 29247060628,
        "averageScore": 5,
        "defaultGoodCount": 2435,
        "defaultGoodCountStr": "2400+",
        "commentCount": 6505,
        "commentCountStr": "6500+",
        "goodCount": 5608,
        "goodCountStr": "5600+",
        "goodRate": 0.97,
        "goodRateShow": 97,
        "generalCount": 61,
        "generalCountStr": "60+",
        "generalRate": 0.01,
        "generalRateShow": 1,
        "poorCount": 65,
        "poorCountStr": "60+",
        "poorRate": 0.02,
        "poorRateShow": 2,
        "videoCount": 0,
        "videoCountStr": "0",
        "afterCount": 252,
        "afterCountStr": "200+",
        "showCount": 0,
        "showCountStr": "0",
        "oneYear": 0,
        "sensitiveBook": 0,
        "fixCount": 1664,
        "plusCount": 0,
        "plusCountStr": "0",
        "buyerShow": 0,
        "poorRateStyle": 3,
        "generalRateStyle": 2,
        "goodRateStyle": 145,
        "installRate": 0,
        "productId": 29247060628,
        "score1Count": 65,
        "score2Count": 17,
        "score3Count": 44,
        "score4Count": 22,
        "score5Count": 3922
    },
    "hotCommentTagStatistics": [
        {
            "id": "7e3c069b0a285d9b",
            "name": "体感舒适",
            "count": 92,
            "type": 4,
            "canBeFiltered": true,
            "stand": 1,
            "rid": "7e3c069b0a285d9b",
            "ckeKeyWordBury": "eid=100^^tagid=7e3c069b0a285d9b^^pid=20027^^sku=29247060628^^sversion=1000^^token=47d116e32883a13b"
        },
        {
            "id": "6640172dc525e1a4",
            "name": "毫无异味",
            "count": 48,
            "type": 4,
            "canBeFiltered": true,
            "stand": 1,
            "rid": "6640172dc525e1a4",
            "ckeKeyWordBury": "eid=100^^tagid=6640172dc525e1a4^^pid=20027^^sku=29247060628^^sversion=1000^^token=3fa63d78ca574396"
        },
        {
            "id": "bb4c03cebcba890a",
            "name": "做工精湛",
            "count": 34,
            "type": 4,
            "canBeFiltered": true,
            "stand": 1,
            "rid": "bb4c03cebcba890a",
            "ckeKeyWordBury": "eid=100^^tagid=bb4c03cebcba890a^^pid=20027^^sku=29247060628^^sversion=1000^^token=d508b6734dbccdba"
        },
        {
            "id": "cfceac32bbcbdd7e",
            "name": "质感一流",
            "count": 29,
            "type": 4,
            "canBeFiltered": true,
            "stand": 1,
            "rid": "cfceac32bbcbdd7e",
            "ckeKeyWordBury": "eid=100^^tagid=cfceac32bbcbdd7e^^pid=20027^^sku=29247060628^^sversion=1000^^token=0ee09b7ac1e39f15"
        },
        {
            "id": "be4c76ce01b83386",
            "name": "简单方便",
            "count": 16,
            "type": 4,
            "canBeFiltered": true,
            "stand": 1,
            "rid": "be4c76ce01b83386",
            "ckeKeyWordBury": "eid=100^^tagid=be4c76ce01b83386^^pid=20027^^sku=29247060628^^sversion=1000^^token=df572aea219495bd"
        },
        {
            "id": "6148130cf344e461",
            "name": "弹性十足",
            "count": 13,
            "type": 4,
            "canBeFiltered": true,
            "stand": 1,
            "rid": "6148130cf344e461",
            "ckeKeyWordBury": "eid=100^^tagid=6148130cf344e461^^pid=20027^^sku=29247060628^^sversion=1000^^token=dc00ea54df854cbf"
        },
        {
            "id": "80f0ec097db263e6",
            "name": "精致美观",
            "count": 11,
            "type": 4,
            "canBeFiltered": true,
            "stand": 1,
            "rid": "80f0ec097db263e6",
            "ckeKeyWordBury": "eid=100^^tagid=80f0ec097db263e6^^pid=20027^^sku=29247060628^^sversion=1000^^token=579e293421b3c671"
        },
        {
            "id": "2aa5d521db4d0cb6",
            "name": "超级好用",
            "count": 10,
            "type": 4,
            "canBeFiltered": true,
            "stand": 1,
            "rid": "2aa5d521db4d0cb6",
            "ckeKeyWordBury": "eid=100^^tagid=2aa5d521db4d0cb6^^pid=20027^^sku=29247060628^^sversion=1000^^token=581fad60461fa976"
        },
        {
            "id": "7ad4b7e72e23b40d",
            "name": "品相一流",
            "count": 6,
            "type": 4,
            "canBeFiltered": true,
            "stand": 1,
            "rid": "7ad4b7e72e23b40d",
            "ckeKeyWordBury": "eid=100^^tagid=7ad4b7e72e23b40d^^pid=20027^^sku=29247060628^^sversion=1000^^token=fb06ed332acbaa83"
        },
        {
            "id": "00fd795eb0227ec3",
            "name": "分量十足",
            "count": 5,
            "type": 4,
            "canBeFiltered": true,
            "stand": 1,
            "rid": "00fd795eb0227ec3",
            "ckeKeyWordBury": "eid=100^^tagid=00fd795eb0227ec3^^pid=20027^^sku=29247060628^^sversion=1000^^token=f007335d48d10dfe"
        },
        {
            "id": "6cdf3b35158951b6",
            "name": "功能齐全",
            "count": 3,
            "type": 4,
            "canBeFiltered": true,
            "stand": 1,
            "rid": "6cdf3b35158951b6",
            "ckeKeyWordBury": "eid=100^^tagid=6cdf3b35158951b6^^pid=20027^^sku=29247060628^^sversion=1000^^token=25b35a3ce92aac36"
        },
        {
            "id": "ffc16b9c644769fc",
            "name": "必备良品",
            "count": 1,
            "type": 4,
            "canBeFiltered": true,
            "stand": 1,
            "rid": "ffc16b9c644769fc",
            "ckeKeyWordBury": "eid=100^^tagid=ffc16b9c644769fc^^pid=20027^^sku=29247060628^^sversion=1000^^token=44cab3fef2063240"
        }
    ],
    "jwotestProduct": null,
    "maxPage": 100,
    "testId": "cmt",
    "score": 0,
    "soType": 5,
    "imageListCount": 0,
    "vTagStatistics": null,
    "csv": "eid=100^^tagid=ALL^^pid=20027^^sku=11723350812^^sversion=1001^^pageSize=34",
    "comments": [
        {
            "id": 13075907528,
            "guid": "34c2042f-b37c-475a-8d1e-424ded21bc64",
            "content": "天啊，外观好逼真，手感也很好，软软的滑滑的。最重要的用起来的感觉贼爽了，会上瘾啊！！！这个用腻了再来换个其他的试试，嘻嘻",
            "vcontent": "",
            "creationTime": "2019-08-02 09:53:24",
            "isDelete": false,
            "isTop": false,
            "userImageUrl": "storage.360buyimg.com/i.imageUpload/c7e9c4d1d7d4bfd8363631353332303438363139373233_sma.jpg",
            "topped": 0,
            "replyCount": 0,
            "score": 5,
            "title": "",
            "usefulVoteCount": 0,
            "userClient": 4,
            "anonymousFlag": 1,
            "plusAvailable": 0,
            "mobileVersion": "8.1.6",
            "productColor": "10斤发音柔情护士拍打叉腿款+VR眼镜+大礼包",
            "productSize": "",
            "textIntegral": 20,
            "status": 1,
            "referenceId": "29247060628",
            "referenceTime": "2019-07-26 09:24:01",
            "nickname": "情***6",
            "replyCount2": 0,
            "userImage": "storage.360buyimg.com/i.imageUpload/c7e9c4d1d7d4bfd8363631353332303438363139373233_sma.jpg",
            "orderId": 0,
            "integral": 20,
            "productSales": "[]",
            "referenceImage": "jfs/t1/89016/7/554/130902/5dafe919E72faaa1b/74b9214702649461.jpg",
            "referenceName": "欢亲飞机杯全自动阴臀倒模1：1名器成人用品男用自慰器充气娃娃全实体硅胶下半身性用品 11斤发音柔情护士拍打叉腿款+VR眼镜+大礼包",
            "firstCategory": 9192,
            "secondCategory": 9196,
            "thirdCategory": 14697,
            "aesPin": null,
            "days": 7,
            "afterDays": 0
        },
        {
            "id": 13075137121,
            "guid": "7bc79120-b2ee-4854-9af8-e4c25c4f92fa",
            "content": "宝贝试用了几次感觉很满意，得到了一种不一样的体验，好评！",
            "vcontent": "",
            "creationTime": "2019-08-01 22:32:36",
            "isDelete": false,
            "isTop": false,
            "userImageUrl": "misc.360buyimg.com/user/myjd-2015/css/i/peisong.jpg",
            "topped": 0,
            "replyCount": 0,
            "score": 5,
            "title": "",
            "usefulVoteCount": 0,
            "userClient": 2,
            "anonymousFlag": 1,
            "plusAvailable": 0,
            "mobileVersion": "6.6.9",
            "productColor": "10斤发音柔情护士拍打叉腿款+VR眼镜+大礼包",
            "productSize": "",
            "textIntegral": 20,
            "status": 1,
            "referenceId": "29247060628",
            "referenceTime": "2019-05-31 21:32:30",
            "nickname": "j***5",
            "replyCount2": 0,
            "userImage": "misc.360buyimg.com/user/myjd-2015/css/i/peisong.jpg",
            "orderId": 0,
            "integral": 20,
            "productSales": "[]",
            "referenceImage": "jfs/t1/89016/7/554/130902/5dafe919E72faaa1b/74b9214702649461.jpg",
            "referenceName": "欢亲飞机杯全自动阴臀倒模1：1名器成人用品男用自慰器充气娃娃全实体硅胶下半身性用品 11斤发音柔情护士拍打叉腿款+VR眼镜+大礼包",
            "firstCategory": 9192,
            "secondCategory": 9196,
            "thirdCategory": 14697,
            "aesPin": null,
            "days": 62,
            "afterDays": 0
        },
        {
            "id": 13073728029,
            "guid": "2b21f81d-3804-4f91-95d7-97724146d929",
            "content": "首先比自撸舒服太多了，柔软像皮肤跟真人接近度比较高，做工非常真，空虚寂寞冷的时候可以拿出来相伴很好。",
            "vcontent": "",
            "creationTime": "2019-08-01 15:03:29",
            "isDelete": false,
            "isTop": false,
            "userImageUrl": "misc.360buyimg.com/user/myjd-2015/css/i/peisong.jpg",
            "topped": 0,
            "replyCount": 0,
            "score": 5,
            "title": "",
            "usefulVoteCount": 0,
            "userClient": 4,
            "anonymousFlag": 1,
            "plusAvailable": 0,
            "mobileVersion": "7.1.0",
            "productColor": "10斤发音柔情护士拍打叉腿款+VR眼镜+大礼包",
            "productSize": "",
            "textIntegral": 20,
            "status": 1,
            "referenceId": "29247060628",
            "referenceTime": "2019-07-26 10:45:44",
            "nickname": "洞***旯",
            "replyCount2": 0,
            "userImage": "misc.360buyimg.com/user/myjd-2015/css/i/peisong.jpg",
            "orderId": 0,
            "integral": 20,
            "productSales": "[]",
            "referenceImage": "jfs/t1/89016/7/554/130902/5dafe919E72faaa1b/74b9214702649461.jpg",
            "referenceName": "欢亲飞机杯全自动阴臀倒模1：1名器成人用品男用自慰器充气娃娃全实体硅胶下半身性用品 11斤发音柔情护士拍打叉腿款+VR眼镜+大礼包",
            "firstCategory": 9192,
            "secondCategory": 9196,
            "thirdCategory": 14697,
            "aesPin": null,
            "days": 6,
            "afterDays": 0
        },
        {
            "id": 13073549811,
            "guid": "eb0354cb-2e11-48f6-8881-2c8866a61f1b",
            "content": "包装的很仔细，也很用心，拆开后看了下非常完整，没有破损的地方，整体上和图片描述的一样，质量上也很好",
            "creationTime": "2019-08-01 14:10:19",
            "isDelete": false,
            "isTop": false,
            "userImageUrl": "misc.360buyimg.com/user/myjd-2015/css/i/peisong.jpg",
            "topped": 0,
            "replyCount": 0,
            "score": 5,
            "title": "",
            "usefulVoteCount": 0,
            "userClient": 21,
            "anonymousFlag": 1,
            "plusAvailable": 0,
            "mobileVersion": "",
            "productColor": "10斤发音柔情护士拍打叉腿款+VR眼镜+大礼包",
            "productSize": "",
            "textIntegral": 0,
            "status": 1,
            "referenceId": "29247060628",
            "referenceTime": "2019-07-26 16:12:30",
            "nickname": "j***4",
            "replyCount2": 0,
            "userImage": "misc.360buyimg.com/user/myjd-2015/css/i/peisong.jpg",
            "orderId": 0,
            "integral": 0,
            "productSales": "[]",
            "referenceImage": "jfs/t1/89016/7/554/130902/5dafe919E72faaa1b/74b9214702649461.jpg",
            "referenceName": "欢亲飞机杯全自动阴臀倒模1：1名器成人用品男用自慰器充气娃娃全实体硅胶下半身性用品 11斤发音柔情护士拍打叉腿款+VR眼镜+大礼包",
            "firstCategory": 9192,
            "secondCategory": 9196,
            "thirdCategory": 14697,
            "aesPin": null,
            "days": 6,
            "afterDays": 0
        },
        {
            "id": 13069688255,
            "guid": "35a2c4a4-98f8-431d-9132-1179a1546d26",
            "content": "娃娃收到了 太美了 包装完好 私密发货  和卖家描述的一样 没有异味 玩起来超爽 叫声也好听 超爽",
            "vcontent": "",
            "creationTime": "2019-07-31 11:18:22",
            "isDelete": false,
            "isTop": false,
            "userImageUrl": "misc.360buyimg.com/user/myjd-2015/css/i/peisong.jpg",
            "topped": 0,
            "replyCount": 0,
            "score": 5,
            "title": "",
            "usefulVoteCount": 0,
            "userClient": 2,
            "anonymousFlag": 1,
            "plusAvailable": 0,
            "mobileVersion": "8.1.6",
            "productColor": "10斤发音柔情护士拍打叉腿款+VR眼镜+大礼包",
            "productSize": "",
            "textIntegral": 20,
            "status": 1,
            "referenceId": "29247060628",
            "referenceTime": "2019-07-25 14:07:57",
            "nickname": "j***0",
            "replyCount2": 0,
            "userImage": "misc.360buyimg.com/user/myjd-2015/css/i/peisong.jpg",
            "orderId": 0,
            "integral": 20,
            "productSales": "[]",
            "referenceImage": "jfs/t1/89016/7/554/130902/5dafe919E72faaa1b/74b9214702649461.jpg",
            "referenceName": "欢亲飞机杯全自动阴臀倒模1：1名器成人用品男用自慰器充气娃娃全实体硅胶下半身性用品 11斤发音柔情护士拍打叉腿款+VR眼镜+大礼包",
            "firstCategory": 9192,
            "secondCategory": 9196,
            "thirdCategory": 14697,
            "aesPin": null,
            "days": 6,
            "afterDays": 0
        },
        {
            "id": 13068242979,
            "guid": "924119fa-1b32-4e04-8e87-0e1f8595775b",
            "content": "宝贝还是很不错的，客服态度非常好，很耐心，之前比较过其他店。赠品也很多，值得拥有",
            "creationTime": "2019-07-30 20:44:09",
            "isDelete": false,
            "isTop": false,
            "userImageUrl": "misc.360buyimg.com/user/myjd-2015/css/i/peisong.jpg",
            "topped": 0,
            "replyCount": 0,
            "score": 5,
            "title": "",
            "usefulVoteCount": 0,
            "userClient": 21,
            "anonymousFlag": 1,
            "plusAvailable": 0,
            "mobileVersion": "",
            "productColor": "10斤发音柔情护士拍打叉腿款+VR眼镜+大礼包",
            "productSize": "",
            "textIntegral": 20,
            "status": 1,
            "referenceId": "29247060628",
            "referenceTime": "2019-07-26 15:08:39",
            "nickname": "q***o",
            "replyCount2": 0,
            "userImage": "misc.360buyimg.com/user/myjd-2015/css/i/peisong.jpg",
            "orderId": 0,
            "integral": 20,
            "productSales": "[]",
            "referenceImage": "jfs/t1/89016/7/554/130902/5dafe919E72faaa1b/74b9214702649461.jpg",
            "referenceName": "欢亲飞机杯全自动阴臀倒模1：1名器成人用品男用自慰器充气娃娃全实体硅胶下半身性用品 11斤发音柔情护士拍打叉腿款+VR眼镜+大礼包",
            "firstCategory": 9192,
            "secondCategory": 9196,
            "thirdCategory": 14697,
            "aesPin": null,
            "days": 4,
            "afterDays": 0
        },
        {
            "id": 13067618476,
            "guid": "f199304e-e96d-4661-9543-f4445702fccc",
            "content": "全实体硅胶的 摸起来软软的 手感特别棒 老板送的礼品也是特别多的哦，丰富的大礼包，尺寸大小刚刚好 玩着很合适",
            "creationTime": "2019-07-30 17:16:48",
            "isDelete": false,
            "isTop": false,
            "userImageUrl": "misc.360buyimg.com/user/myjd-2015/css/i/peisong.jpg",
            "topped": 0,
            "replyCount": 0,
            "score": 5,
            "title": "",
            "usefulVoteCount": 0,
            "userClient": 21,
            "anonymousFlag": 0,
            "plusAvailable": 0,
            "mobileVersion": "",
            "productColor": "10斤发音柔情护士拍打叉腿款+VR眼镜+大礼包",
            "productSize": "",
            "textIntegral": 20,
            "status": 1,
            "referenceId": "29247060628",
            "referenceTime": "2019-07-26 15:05:42",
            "nickname": "j***0",
            "replyCount2": 0,
            "userImage": "misc.360buyimg.com/user/myjd-2015/css/i/peisong.jpg",
            "orderId": 0,
            "integral": 20,
            "productSales": "[]",
            "referenceImage": "jfs/t1/89016/7/554/130902/5dafe919E72faaa1b/74b9214702649461.jpg",
            "referenceName": "欢亲飞机杯全自动阴臀倒模1：1名器成人用品男用自慰器充气娃娃全实体硅胶下半身性用品 11斤发音柔情护士拍打叉腿款+VR眼镜+大礼包",
            "firstCategory": 9192,
            "secondCategory": 9196,
            "thirdCategory": 14697,
            "aesPin": "KRU9Lb85emwYbJsVv0uYlK45J3y6GTB386g9eNh43aDwdAOxDErh3GjYqBqAl5A588J6HWasRwqDWTcfwO9L2g",
            "days": 4,
            "afterDays": 0
        },
        {
            "id": 13063980508,
            "guid": "dc49dd93-50a2-4a05-9e31-fef06f90a266",
            "content": "非常给力啊！再加点润滑油感觉比真人爽啊！一看就是正品的，性价比也比较好，服务态度超级好，物流非一般的快",
            "creationTime": "2019-07-29 16:12:27",
            "isDelete": false,
            "isTop": false,
            "userImageUrl": "misc.360buyimg.com/user/myjd-2015/css/i/peisong.jpg",
            "topped": 0,
            "replyCount": 0,
            "score": 5,
            "title": "",
            "usefulVoteCount": 0,
            "userClient": 4,
            "anonymousFlag": 1,
            "plusAvailable": 201,
            "mobileVersion": "8.1.6",
            "productColor": "10斤发音柔情护士拍打叉腿款+VR眼镜+大礼包",
            "productSize": "",
            "textIntegral": 20,
            "status": 1,
            "referenceId": "29247060628",
            "referenceTime": "2019-07-24 10:02:53",
            "nickname": "j***n",
            "replyCount2": 0,
            "userImage": "misc.360buyimg.com/user/myjd-2015/css/i/peisong.jpg",
            "orderId": 0,
            "integral": 20,
            "productSales": "[]",
            "referenceImage": "jfs/t1/89016/7/554/130902/5dafe919E72faaa1b/74b9214702649461.jpg",
            "referenceName": "欢亲飞机杯全自动阴臀倒模1：1名器成人用品男用自慰器充气娃娃全实体硅胶下半身性用品 11斤发音柔情护士拍打叉腿款+VR眼镜+大礼包",
            "firstCategory": 9192,
            "secondCategory": 9196,
            "thirdCategory": 14697,
            "aesPin": null,
            "days": 5,
            "afterDays": 0
        },
        {
            "id": 13063670045,
            "guid": "374be649-7203-4c87-ade8-0898880b1f4c",
            "content": "玩起来的效果实在是太强了啊，不得不赞一个，这货太勾引人了啊，不过我很是喜欢啊！做起来就像个超级软妹子！做工赞，这个包裹的确是非常严密的啊！质量也是特别的好，材质特别柔软，手感超级好的哎。使用起来的感觉是真的爽爽的啊，撸友们可以考虑入手的",
            "creationTime": "2019-07-29 14:50:14",
            "isDelete": false,
            "isTop": false,
            "userImageUrl": "misc.360buyimg.com/user/myjd-2015/css/i/peisong.jpg",
            "topped": 0,
            "replyCount": 0,
            "score": 5,
            "title": "",
            "usefulVoteCount": 0,
            "userClient": 4,
            "anonymousFlag": 1,
            "plusAvailable": 103,
            "mobileVersion": "8.1.6",
            "productColor": "10斤发音柔情护士拍打叉腿款+VR眼镜+大礼包",
            "productSize": "",
            "textIntegral": 20,
            "status": 1,
            "referenceId": "29247060628",
            "referenceTime": "2019-07-26 09:26:41",
            "nickname": "E***Z",
            "replyCount2": 0,
            "userImage": "misc.360buyimg.com/user/myjd-2015/css/i/peisong.jpg",
            "orderId": 0,
            "integral": 20,
            "productSales": "[]",
            "referenceImage": "jfs/t1/89016/7/554/130902/5dafe919E72faaa1b/74b9214702649461.jpg",
            "referenceName": "欢亲飞机杯全自动阴臀倒模1：1名器成人用品男用自慰器充气娃娃全实体硅胶下半身性用品 11斤发音柔情护士拍打叉腿款+VR眼镜+大礼包",
            "firstCategory": 9192,
            "secondCategory": 9196,
            "thirdCategory": 14697,
            "aesPin": null,
            "days": 3,
            "afterDays": 0
        },
        {
            "id": 13062663092,
            "guid": "9744ad20-aa93-4fc7-8f4c-670eb28553bc",
            "content": "手感舒适，宝贝材质摸上去滑滑的，东西无味有感觉，没有异味，质量也是相当过硬，真的很喜欢。而且包裹也很隐私，没有泄露一点信息，服务很好材质很柔软，摸着很有手感，做工很精致，用着舒服",
            "creationTime": "2019-07-29 10:30:55",
            "isDelete": false,
            "isTop": false,
            "userImageUrl": "misc.360buyimg.com/user/myjd-2015/css/i/peisong.jpg",
            "topped": 0,
            "replyCount": 0,
            "score": 5,
            "title": "",
            "usefulVoteCount": 0,
            "userClient": 21,
            "anonymousFlag": 1,
            "plusAvailable": 0,
            "mobileVersion": "",
            "productColor": "10斤发音柔情护士拍打叉腿款+VR眼镜+大礼包",
            "productSize": "",
            "textIntegral": 20,
            "status": 1,
            "referenceId": "29247060628",
            "referenceTime": "2019-07-11 17:49:49",
            "nickname": "j***5",
            "replyCount2": 0,
            "userImage": "misc.360buyimg.com/user/myjd-2015/css/i/peisong.jpg",
            "orderId": 0,
            "integral": 20,
            "productSales": "[]",
            "referenceImage": "jfs/t1/89016/7/554/130902/5dafe919E72faaa1b/74b9214702649461.jpg",
            "referenceName": "欢亲飞机杯全自动阴臀倒模1：1名器成人用品男用自慰器充气娃娃全实体硅胶下半身性用品 11斤发音柔情护士拍打叉腿款+VR眼镜+大礼包",
            "firstCategory": 9192,
            "secondCategory": 9196,
            "thirdCategory": 14697,
            "aesPin": null,
            "days": 18,
            "afterDays": 0
        }
    ]
}