{
    "productAttr": null,
    "productCommentSummary": {
        "skuId": 58156667745,
        "averageScore": 5,
        "defaultGoodCount": 140,
        "defaultGoodCountStr": "100+",
        "commentCount": 432,
        "commentCountStr": "400+",
        "goodCount": 286,
        "goodCountStr": "200+",
        "goodRate": 0.97,
        "goodRateShow": 97,
        "generalCount": 3,
        "generalCountStr": "3",
        "generalRate": 0.02,
        "generalRateShow": 2,
        "poorCount": 3,
        "poorCountStr": "3",
        "poorRate": 0.01,
        "poorRateShow": 1,
        "videoCount": 0,
        "videoCountStr": "0",
        "afterCount": 8,
        "afterCountStr": "8",
        "showCount": 0,
        "showCountStr": "0",
        "oneYear": 0,
        "sensitiveBook": 0,
        "fixCount": 0,
        "plusCount": 0,
        "plusCountStr": "0",
        "buyerShow": 0,
        "poorRateStyle": 2,
        "generalRateStyle": 3,
        "goodRateStyle": 145,
        "installRate": 0,
        "productId": 58156667745,
        "score1Count": 3,
        "score2Count": 1,
        "score3Count": 2,
        "score4Count": 0,
        "score5Count": 286
    },
    "hotCommentTagStatistics": [
        {
            "id": "7e3c069b0a285d9b",
            "name": "体感舒适",
            "count": 16,
            "type": 4,
            "canBeFiltered": true,
            "stand": 1,
            "rid": "7e3c069b0a285d9b",
            "ckeKeyWordBury": "eid=100^^tagid=7e3c069b0a285d9b^^pid=20027^^sku=58156667745^^sversion=1000^^token=03b90d14e38bf419"
        },
        {
            "id": "bb4c03cebcba890a",
            "name": "做工精湛",
            "count": 10,
            "type": 4,
            "canBeFiltered": true,
            "stand": 1,
            "rid": "bb4c03cebcba890a",
            "ckeKeyWordBury": "eid=100^^tagid=bb4c03cebcba890a^^pid=20027^^sku=58156667745^^sversion=1000^^token=ad354772dd8c57ea"
        },
        {
            "id": "6640172dc525e1a4",
            "name": "毫无异味",
            "count": 10,
            "type": 4,
            "canBeFiltered": true,
            "stand": 1,
            "rid": "6640172dc525e1a4",
            "ckeKeyWordBury": "eid=100^^tagid=6640172dc525e1a4^^pid=20027^^sku=58156667745^^sversion=1000^^token=0e139aeb20663cdb"
        },
        {
            "id": "2aa5d521db4d0cb6",
            "name": "超级好用",
            "count": 4,
            "type": 4,
            "canBeFiltered": true,
            "stand": 1,
            "rid": "2aa5d521db4d0cb6",
            "ckeKeyWordBury": "eid=100^^tagid=2aa5d521db4d0cb6^^pid=20027^^sku=58156667745^^sversion=1000^^token=31539e33b5c80deb"
        },
        {
            "id": "be4c76ce01b83386",
            "name": "简单方便",
            "count": 2,
            "type": 4,
            "canBeFiltered": true,
            "stand": 1,
            "rid": "be4c76ce01b83386",
            "ckeKeyWordBury": "eid=100^^tagid=be4c76ce01b83386^^pid=20027^^sku=58156667745^^sversion=1000^^token=438871d91cf2f58f"
        },
        {
            "id": "cfceac32bbcbdd7e",
            "name": "质感一流",
            "count": 2,
            "type": 4,
            "canBeFiltered": true,
            "stand": 1,
            "rid": "cfceac32bbcbdd7e",
            "ckeKeyWordBury": "eid=100^^tagid=cfceac32bbcbdd7e^^pid=20027^^sku=58156667745^^sversion=1000^^token=29bb833860a9b1a0"
        },
        {
            "id": "8d5387624e70bbd2",
            "name": "质地细腻",
            "count": 2,
            "type": 4,
            "canBeFiltered": true,
            "stand": 1,
            "rid": "8d5387624e70bbd2",
            "ckeKeyWordBury": "eid=100^^tagid=8d5387624e70bbd2^^pid=20027^^sku=58156667745^^sversion=1000^^token=ef3de37bcf8b9469"
        },
        {
            "id": "6148130cf344e461",
            "name": "弹性十足",
            "count": 2,
            "type": 4,
            "canBeFiltered": true,
            "stand": 1,
            "rid": "6148130cf344e461",
            "ckeKeyWordBury": "eid=100^^tagid=6148130cf344e461^^pid=20027^^sku=58156667745^^sversion=1000^^token=9be2ac1aa7a00035"
        },
        {
            "id": "f3225ba62d01698a",
            "name": "尺寸适宜",
            "count": 2,
            "type": 4,
            "canBeFiltered": true,
            "stand": 1,
            "rid": "f3225ba62d01698a",
            "ckeKeyWordBury": "eid=100^^tagid=f3225ba62d01698a^^pid=20027^^sku=58156667745^^sversion=1000^^token=2b604164d66d3f0c"
        }
    ],
    "jwotestProduct": null,
    "maxPage": 17,
    "testId": "cmt",
    "score": 0,
    "soType": 5,
    "imageListCount": 0,
    "vTagStatistics": null,
    "csv": "eid=100^^tagid=ALL^^pid=20027^^sku=13702307458^^sversion=1001^^pageSize=10",
    "comments": [
        {
            "id": 13683186863,
            "guid": "ed3e5a5e-d0ce-4e4f-83f8-4be6f9c32dde",
            "content": "还不错 物流速度很快 客服态度非常好 很有耐心",
            "creationTime": "2020-01-04 18:10:33",
            "isDelete": false,
            "isTop": false,
            "userImageUrl": "misc.360buyimg.com/user/myjd-2015/css/i/peisong.jpg",
            "topped": 0,
            "replyCount": 0,
            "score": 5,
            "title": "",
            "usefulVoteCount": 0,
            "userClient": 4,
            "anonymousFlag": 1,
            "plusAvailable": 0,
            "mobileVersion": "",
            "productColor": "羞涩小妹3.2斤+震动发音+体验礼包",
            "productSize": "",
            "textIntegral": 10,
            "status": 1,
            "referenceId": "58156667745",
            "referenceTime": "2019-12-25 22:29:59",
            "nickname": "马***妞",
            "replyCount2": 0,
            "userImage": "misc.360buyimg.com/user/myjd-2015/css/i/peisong.jpg",
            "orderId": 0,
            "integral": 10,
            "productSales": "[]",
            "referenceImage": "jfs/t1/109466/13/4827/94126/5e256fccE1f5b249b/6a5e9f620ab5022e.jpg",
            "referenceName": "MAIG飞机男用非充气倒美臀名器实体硅胶半身娃娃阴臀倒模1：1男士用品成人用品情趣男性自慰器乳jq 羞涩小妹3.2斤+大礼包",
            "firstCategory": 9192,
            "secondCategory": 9196,
            "thirdCategory": 14697,
            "aesPin": null,
            "days": 11,
            "afterDays": 0
        },
        {
            "id": 13676885313,
            "guid": "5d5e844e-9cb5-4c83-a09f-8e8479a1d241",
            "content": "倒入一点润滑油进去的，润滑的感觉非常舒服刺激，进去之后的感觉很温润，感觉内壁做的非常细腻",
            "creationTime": "2020-01-03 07:33:10",
            "isDelete": false,
            "isTop": false,
            "userImageUrl": "misc.360buyimg.com/user/myjd-2015/css/i/peisong.jpg",
            "topped": 0,
            "replyCount": 0,
            "score": 5,
            "title": "",
            "usefulVoteCount": 0,
            "userClient": 2,
            "anonymousFlag": 1,
            "plusAvailable": 0,
            "mobileVersion": "",
            "productColor": "羞涩小妹3.2斤+震动发音+体验礼包",
            "productSize": "",
            "textIntegral": 10,
            "status": 1,
            "referenceId": "58156667745",
            "referenceTime": "2019-12-28 19:21:21",
            "nickname": "j***y",
            "replyCount2": 0,
            "userImage": "misc.360buyimg.com/user/myjd-2015/css/i/peisong.jpg",
            "orderId": 0,
            "integral": 10,
            "productSales": "[]",
            "referenceImage": "jfs/t1/109466/13/4827/94126/5e256fccE1f5b249b/6a5e9f620ab5022e.jpg",
            "referenceName": "MAIG飞机男用非充气倒美臀名器实体硅胶半身娃娃阴臀倒模1：1男士用品成人用品情趣男性自慰器乳jq 羞涩小妹3.2斤+大礼包",
            "firstCategory": 9192,
            "secondCategory": 9196,
            "thirdCategory": 14697,
            "aesPin": null,
            "days": 7,
            "afterDays": 0
        },
        {
            "id": 13679529140,
            "guid": "38fbf702-0895-465d-80f4-6b2cc1b39b6a",
            "content": "收到当晚就用了，从包装到内函均精致上档次，手感柔软，插它就像查***一样，**里面凸起的颗粒好真实，搞的酥酥麻麻的.比用手撸的感觉好太多了配合***使用感觉太棒了。",
            "creationTime": "2020-01-03 19:13:12",
            "isDelete": false,
            "isTop": false,
            "userImageUrl": "misc.360buyimg.com/user/myjd-2015/css/i/peisong.jpg",
            "topped": 0,
            "replyCount": 0,
            "score": 5,
            "title": "",
            "usefulVoteCount": 0,
            "userClient": 4,
            "anonymousFlag": 1,
            "plusAvailable": 0,
            "mobileVersion": "",
            "productColor": "羞涩小妹3.2斤+震动发音+体验礼包",
            "productSize": "",
            "textIntegral": 10,
            "status": 1,
            "referenceId": "58156667745",
            "referenceTime": "2019-12-30 19:01:00",
            "nickname": "阿***-",
            "replyCount2": 0,
            "userImage": "misc.360buyimg.com/user/myjd-2015/css/i/peisong.jpg",
            "orderId": 0,
            "integral": 10,
            "productSales": "[]",
            "referenceImage": "jfs/t1/109466/13/4827/94126/5e256fccE1f5b249b/6a5e9f620ab5022e.jpg",
            "referenceName": "MAIG飞机男用非充气倒美臀名器实体硅胶半身娃娃阴臀倒模1：1男士用品成人用品情趣男性自慰器乳jq 羞涩小妹3.2斤+大礼包",
            "firstCategory": 9192,
            "secondCategory": 9196,
            "thirdCategory": 14697,
            "aesPin": null,
            "days": 5,
            "afterDays": 0
        },
        {
            "id": 13674642621,
            "guid": "0403a030-f999-41f7-85e9-e51c34bdb043",
            "content": "包装完好，体验感特别棒，遇水即顺滑，感觉特别爽，肤质和手感还有做工都特别好，爱了，满意的一次购物。、",
            "creationTime": "2020-01-02 15:46:38",
            "isDelete": false,
            "isTop": false,
            "userImageUrl": "storage.360buyimg.com/i.imageUpload/6a645f3535383366643666363665366631353130333834303231383534_sma.jpg",
            "topped": 0,
            "replyCount": 0,
            "score": 5,
            "title": "",
            "usefulVoteCount": 0,
            "userClient": 4,
            "anonymousFlag": 1,
            "plusAvailable": 0,
            "mobileVersion": "",
            "productColor": "迷你小娇娃600g",
            "productSize": "",
            "textIntegral": 10,
            "status": 1,
            "referenceId": "58156667744",
            "referenceTime": "2019-12-20 10:11:33",
            "nickname": "勇***3",
            "replyCount2": 0,
            "userImage": "storage.360buyimg.com/i.imageUpload/6a645f3535383366643666363665366631353130333834303231383534_sma.jpg",
            "orderId": 0,
            "integral": 10,
            "productSales": "[]",
            "referenceImage": "jfs/t1/109466/13/4827/94126/5e256fccE1f5b249b/6a5e9f620ab5022e.jpg",
            "referenceName": "MAIG飞机男用非充气倒美臀名器实体硅胶半身娃娃阴臀倒模1：1男士用品成人用品情趣男性自慰器乳jq 羞涩小妹3.2斤+大礼包",
            "firstCategory": 9192,
            "secondCategory": 9196,
            "thirdCategory": 14697,
            "aesPin": null,
            "days": 14,
            "afterDays": 0
        },
        {
            "id": 13675625109,
            "guid": "567ed6ff-9b64-45c7-9bc6-ea55a3a86880",
            "content": "很好用的一款产品，发货很保密，速度一流",
            "creationTime": "2020-01-02 19:44:10",
            "isDelete": false,
            "isTop": false,
            "userImageUrl": "misc.360buyimg.com/user/myjd-2015/css/i/peisong.jpg",
            "topped": 0,
            "replyCount": 0,
            "score": 5,
            "title": "",
            "usefulVoteCount": 0,
            "userClient": 4,
            "anonymousFlag": 1,
            "plusAvailable": 0,
            "mobileVersion": "",
            "productColor": "羞涩小妹3.2斤+震动发音+体验礼包",
            "productSize": "",
            "textIntegral": 10,
            "status": 1,
            "referenceId": "58156667745",
            "referenceTime": "2019-12-31 16:35:19",
            "nickname": "X***_",
            "replyCount2": 0,
            "userImage": "misc.360buyimg.com/user/myjd-2015/css/i/peisong.jpg",
            "orderId": 0,
            "integral": 10,
            "productSales": "[]",
            "referenceImage": "jfs/t1/109466/13/4827/94126/5e256fccE1f5b249b/6a5e9f620ab5022e.jpg",
            "referenceName": "MAIG飞机男用非充气倒美臀名器实体硅胶半身娃娃阴臀倒模1：1男士用品成人用品情趣男性自慰器乳jq 羞涩小妹3.2斤+大礼包",
            "firstCategory": 9192,
            "secondCategory": 9196,
            "thirdCategory": 14697,
            "aesPin": null,
            "days": 3,
            "afterDays": 0
        },
        {
            "id": 13675027036,
            "guid": "cbfd6d1d-5134-4230-b230-764d68208a03",
            "content": "非常舒服",
            "creationTime": "2020-01-02 17:20:54",
            "isDelete": false,
            "isTop": false,
            "userImageUrl": "misc.360buyimg.com/user/myjd-2015/css/i/peisong.jpg",
            "topped": 0,
            "replyCount": 0,
            "score": 5,
            "usefulVoteCount": 0,
            "userClient": 4,
            "anonymousFlag": 1,
            "plusAvailable": 0,
            "mobileVersion": "",
            "productColor": "迷你小娇娃600g",
            "textIntegral": 0,
            "status": 1,
            "referenceId": "58156667744",
            "referenceTime": "2019-12-31 18:20:54",
            "nickname": "D***H",
            "replyCount2": 0,
            "userImage": "misc.360buyimg.com/user/myjd-2015/css/i/peisong.jpg",
            "orderId": 0,
            "integral": 0,
            "productSales": "[]",
            "referenceImage": "jfs/t1/109466/13/4827/94126/5e256fccE1f5b249b/6a5e9f620ab5022e.jpg",
            "referenceName": "MAIG飞机男用非充气倒美臀名器实体硅胶半身娃娃阴臀倒模1：1男士用品成人用品情趣男性自慰器乳jq 羞涩小妹3.2斤+大礼包",
            "firstCategory": 9192,
            "secondCategory": 9196,
            "thirdCategory": 14697,
            "aesPin": null,
            "days": 3,
            "afterDays": 0
        },
        {
            "id": 13675003852,
            "guid": "060be0ed-03ca-4dc8-a693-893df3c1af85",
            "content": "很好用的一款产品，手感柔软有弹性，效果逼真摸起来就像真人一样的",
            "creationTime": "2020-01-02 17:15:27",
            "isDelete": false,
            "isTop": false,
            "userImageUrl": "misc.360buyimg.com/user/myjd-2015/css/i/peisong.jpg",
            "topped": 0,
            "replyCount": 0,
            "score": 5,
            "title": "",
            "usefulVoteCount": 0,
            "userClient": 4,
            "anonymousFlag": 0,
            "plusAvailable": 0,
            "mobileVersion": "",
            "productColor": "羞涩小妹3.2斤+震动发音+体验礼包",
            "productSize": "",
            "textIntegral": 10,
            "status": 1,
            "referenceId": "58156667745",
            "referenceTime": "2019-12-31 17:27:23",
            "nickname": "tangMin97",
            "replyCount2": 0,
            "userImage": "misc.360buyimg.com/user/myjd-2015/css/i/peisong.jpg",
            "orderId": 0,
            "integral": 10,
            "productSales": "[]",
            "referenceImage": "jfs/t1/109466/13/4827/94126/5e256fccE1f5b249b/6a5e9f620ab5022e.jpg",
            "referenceName": "MAIG飞机男用非充气倒美臀名器实体硅胶半身娃娃阴臀倒模1：1男士用品成人用品情趣男性自慰器乳jq 羞涩小妹3.2斤+大礼包",
            "firstCategory": 9192,
            "secondCategory": 9196,
            "thirdCategory": 14697,
            "aesPin": "Z9UYbmHIyOZOXmnufR9_iUL1Jsf4ZxKUZHREKkDWIVEttgSkB0hQc_7iDJTJSrPTSpRRzU2hK44RVHcG-JGGoA",
            "days": 3,
            "afterDays": 0
        },
        {
            "id": 13670832869,
            "guid": "27413c32-b056-43c9-a143-c7d91a499370",
            "content": "娃娃看起来很逼真，用起来也很逼真，物美价廉，真的爱不释手，保密发货，大家放心购买",
            "creationTime": "2020-01-01 16:28:46",
            "isDelete": false,
            "isTop": false,
            "userImageUrl": "storage.360buyimg.com/i.imageUpload/6a645f3463633633633136616462313431353238373733343336363533_sma.jpg",
            "topped": 0,
            "replyCount": 0,
            "score": 5,
            "usefulVoteCount": 0,
            "userClient": 2,
            "anonymousFlag": 1,
            "plusAvailable": 0,
            "mobileVersion": "",
            "productColor": "羞涩小妹3.2斤+震动发音+体验礼包",
            "textIntegral": 10,
            "status": 1,
            "referenceId": "58156667745",
            "referenceTime": "2019-12-23 20:27:27",
            "nickname": "唯***s",
            "replyCount2": 0,
            "userImage": "storage.360buyimg.com/i.imageUpload/6a645f3463633633633136616462313431353238373733343336363533_sma.jpg",
            "orderId": 0,
            "integral": 10,
            "productSales": "[]",
            "referenceImage": "jfs/t1/109466/13/4827/94126/5e256fccE1f5b249b/6a5e9f620ab5022e.jpg",
            "referenceName": "MAIG飞机男用非充气倒美臀名器实体硅胶半身娃娃阴臀倒模1：1男士用品成人用品情趣男性自慰器乳jq 羞涩小妹3.2斤+大礼包",
            "firstCategory": 9192,
            "secondCategory": 9196,
            "thirdCategory": 14697,
            "aesPin": null,
            "days": 10,
            "afterDays": 0
        },
        {
            "id": 13671755351,
            "guid": "c158ec51-71ec-41ed-b7e1-4230d1506d94",
            "content": "产品柔软无异味很逼真，玩起来舒服爽",
            "creationTime": "2020-01-01 20:28:00",
            "isDelete": false,
            "isTop": false,
            "userImageUrl": "misc.360buyimg.com/user/myjd-2015/css/i/peisong.jpg",
            "topped": 0,
            "replyCount": 0,
            "score": 5,
            "title": "",
            "usefulVoteCount": 0,
            "userClient": 4,
            "anonymousFlag": 1,
            "plusAvailable": 0,
            "mobileVersion": "",
            "productColor": "羞涩小妹3.2斤+震动发音+体验礼包",
            "productSize": "",
            "textIntegral": 10,
            "status": 1,
            "referenceId": "58156667745",
            "referenceTime": "2019-12-26 11:09:29",
            "nickname": "j***t",
            "replyCount2": 0,
            "userImage": "misc.360buyimg.com/user/myjd-2015/css/i/peisong.jpg",
            "orderId": 0,
            "integral": 10,
            "productSales": "[]",
            "referenceImage": "jfs/t1/109466/13/4827/94126/5e256fccE1f5b249b/6a5e9f620ab5022e.jpg",
            "referenceName": "MAIG飞机男用非充气倒美臀名器实体硅胶半身娃娃阴臀倒模1：1男士用品成人用品情趣男性自慰器乳jq 羞涩小妹3.2斤+大礼包",
            "firstCategory": 9192,
            "secondCategory": 9196,
            "thirdCategory": 14697,
            "aesPin": null,
            "days": 7,
            "afterDays": 0
        },
        {
            "id": 13671048812,
            "guid": "ba51f96b-0811-4384-a959-48601502ba1f",
            "content": "体验了觉得性价比很好了这个价格超值",
            "creationTime": "2020-01-01 17:26:35",
            "isDelete": false,
            "isTop": false,
            "userImageUrl": "misc.360buyimg.com/user/myjd-2015/css/i/peisong.jpg",
            "topped": 0,
            "replyCount": 0,
            "score": 5,
            "usefulVoteCount": 0,
            "userClient": 4,
            "anonymousFlag": 1,
            "plusAvailable": 0,
            "mobileVersion": "",
            "productColor": "羞涩小妹3.2斤+震动发音+体验礼包",
            "textIntegral": 10,
            "status": 1,
            "referenceId": "58156667745",
            "referenceTime": "2019-12-27 21:11:52",
            "nickname": "j***2",
            "replyCount2": 0,
            "userImage": "misc.360buyimg.com/user/myjd-2015/css/i/peisong.jpg",
            "orderId": 0,
            "integral": 10,
            "productSales": "[]",
            "referenceImage": "jfs/t1/109466/13/4827/94126/5e256fccE1f5b249b/6a5e9f620ab5022e.jpg",
            "referenceName": "MAIG飞机男用非充气倒美臀名器实体硅胶半身娃娃阴臀倒模1：1男士用品成人用品情趣男性自慰器乳jq 羞涩小妹3.2斤+大礼包",
            "firstCategory": 9192,
            "secondCategory": 9196,
            "thirdCategory": 14697,
            "aesPin": null,
            "days": 6,
            "afterDays": 0
        }
    ]
}